nestipy_socialite/__init__.py
nestipy_socialite/builder.py
nestipy_socialite/config.py
nestipy_socialite/exception.py
nestipy_socialite/module.py
nestipy_socialite/providers/__init__.py
nestipy_socialite/providers/abstract.py
nestipy_socialite/providers/azure.py
nestipy_socialite/providers/facebook.py
nestipy_socialite/providers/github.py
nestipy_socialite/providers/google.py
nestipy_socialite/providers/instagram.py
nestipy_socialite/providers/linkedin.py
nestipy_socialite/providers/microsoft.py
nestipy_socialite/providers/spotify.py
nestipy_socialite/providers/x.py
nestipy_socialite/service.py
nestipy_socialite-0.1.2.dist-info/LICENSE
nestipy_socialite-0.1.2.dist-info/METADATA
nestipy_socialite-0.1.2.dist-info/WHEEL
nestipy_socialite-0.1.2.dist-info/RECORD
