Metadata-Version: 2.1
Name: nestipy-socialite
Version: 0.1.2
Summary: Nestipy pakcage for social network authentification
Author: Tsiresy Milà
Author-email: tsiresymila@gmail.com
Requires-Python: >=3.11,<4.0
Classifier: Programming Language :: Python :: 3
Classifier: Programming Language :: Python :: 3.11
Classifier: Programming Language :: Python :: 3.12
Classifier: Programming Language :: Python :: 3.13
Requires-Dist: requests-oauthlib (>=2.0.0,<3.0.0)
